insitupy/__init__.py
insitupy/_checks.py
insitupy/_constants.py
insitupy/_core/__init__.py
insitupy/_core/_checks.py
insitupy/_core/_deprecated.py
insitupy/_core/data.py
insitupy/_deprecated/_deprecated.py
insitupy/_deprecated/_spatialdata.py
insitupy/_exceptions.py
insitupy/_io/_qupath.py
insitupy/_io/_read.py
insitupy/_io/_xenium.py
insitupy/_io/files.py
insitupy/_io/geo.py
insitupy/_mixins.py
insitupy/_textformat.py
insitupy/_warnings.py
insitupy/_xenium_panels/Xenium_hBrain_v1_metadata.csv
insitupy/_xenium_panels/Xenium_hBreast_v1_metadata.csv
insitupy/_xenium_panels/Xenium_hLung_v1_metadata.csv
insitupy/_xenium_panels/Xenium_hMulti_v1_metadata.csv
insitupy/_xenium_panels/Xenium_mBrain_v1.1_metadata.csv
insitupy/dataclasses/__init__.py
insitupy/dataclasses/_segmentations.py
insitupy/dataclasses/_utils.py
insitupy/dataclasses/dataclasses.py
insitupy/dataclasses/io.py
insitupy/dataclasses/results.py
insitupy/datasets/__init__.py
insitupy/datasets/datasets.py
insitupy/datasets/download.py
insitupy/datasets/README.md
insitupy/experiment/__init__.py
insitupy/experiment/_checks.py
insitupy/experiment/_deprecated.py
insitupy/experiment/data.py
insitupy/images/__init__.py
insitupy/images/axes.py
insitupy/images/io.py
insitupy/images/utils.py
insitupy/interactive/__init__.py
insitupy/interactive/_callbacks.py
insitupy/interactive/_checks.py
insitupy/interactive/_configs.py
insitupy/interactive/_layers.py
insitupy/interactive/_widgets.py
insitupy/interactive/viewer.py
insitupy/io/__init__.py
insitupy/io/data.py
insitupy/io/experiment.py
insitupy/palettes.py
insitupy/plotting/__init__.py
insitupy/plotting/config.py
insitupy/plotting/dge.py
insitupy/plotting/expression_along_axis.py
insitupy/plotting/facs.py
insitupy/plotting/go.py
insitupy/plotting/overview.py
insitupy/plotting/plots.py
insitupy/plotting/qc.py
insitupy/plotting/save.py
insitupy/plotting/spatial.py
insitupy/plotting/spatial_old.py
insitupy/plotting/volcano.py
insitupy/preprocessing/__init__.py
insitupy_spatial-0.10.3.dist-info/LICENSE
insitupy_spatial-0.10.3.dist-info/METADATA
insitupy_spatial-0.10.3.dist-info/WHEEL
insitupy_spatial-0.10.3.dist-info/RECORD
