Metadata-Version: 2.3
Name: insitupy-spatial
Version: 0.10.3
Summary: Package introducing the InSituPy framework to analyze single-cell spatial transcriptomics data.
License: BSD-3-Clause
Author: Johannes Wirth
Author-email: jwrth <j.wirth@tum.de>
Requires-Python: >=3.10.0,<3.11.0
Classifier: License :: OSI Approved :: BSD License
Classifier: Programming Language :: Python :: 3
Classifier: Programming Language :: Python :: 3.10
Provides-Extra: gui
Requires-Dist: adjusttext (>=1.3.0,<2.0.0)
Requires-Dist: dask (>=2025.3.0,<2025.12.0)
Requires-Dist: dask-geopandas (>=0.4.2)
Requires-Dist: dask-image (>=2023.8.1)
Requires-Dist: decoupler (>=2.1.1,<3.0.0)
Requires-Dist: fastparquet (>=2023.10.1)
Requires-Dist: fiona (>=1.10.1)
Requires-Dist: geopandas (>=1.0.1)
Requires-Dist: imagecodecs (>=2024.12.30)
Requires-Dist: napari[all] (>=0.5.6,<0.6.3) ; extra == "gui"
Requires-Dist: numpy (>=2.1.3,<3.0.0)
Requires-Dist: opencv-python (>=4.8.0.76)
Requires-Dist: openpyxl (>=3.1.2,<4.0.0)
Requires-Dist: parse (>=1.19.1)
Requires-Dist: plottable (==0.1.5)
Requires-Dist: pyarrow (>=14.0.1,<=21.0.0)
Requires-Dist: pytest (>=7.4.2)
Requires-Dist: rasterio (>=1.4.3)
Requires-Dist: requests
Requires-Dist: scanpy[leiden] (>=1.10.3,<2.0.0)
Requires-Dist: scikit-image (>=0.21.0,<1.0.0)
Requires-Dist: scikit-misc (>=0.3.1)
Requires-Dist: toml (>=0.10.2,<1.0.0)
Requires-Dist: tornado (>=6.5.0)
Requires-Dist: xmltodict (>=0.13.0)
Requires-Dist: zarr (>=2.16.1,<3.0.0)
